rijndael3d/__init__.py
rijndael3d/block.py
rijndael3d/cipher.py
rijndael3d/constants.py
rijndael3d/debug_operations.py
rijndael3d/gf_arithmetic.py
rijndael3d/key_schedule.py
rijndael3d/modes/cbc.py
rijndael3d/modes/ctr.py
rijndael3d/modes/ecb.py
rijndael3d/modes/gcm.py
rijndael3d/padding.py
rijndael3d/utils.py
rijndael3d-1.1.1.dist-info/LICENSE
rijndael3d-1.1.1.dist-info/METADATA
rijndael3d-1.1.1.dist-info/WHEEL
rijndael3d-1.1.1.dist-info/RECORD
