Metadata-Version: 2.3
Name: rijndael3d
Version: 1.1.1
Summary: An enhanced version of Rijndael encryption
License: MIT
Author: Jebbex
Author-email: 107323805+Jebbex1@users.noreply.github.com
Requires-Python: >=3.13
Classifier: License :: OSI Approved :: MIT License
Classifier: Programming Language :: Python :: 3
Classifier: Programming Language :: Python :: 3.13
Requires-Dist: numba (>=0.61.2,<0.62.0)
